lyrics_hunter/__init__.py
lyrics_hunter/hunter.py
test/__init__.py
test/test_hunter.py
lyrics_hunter-11.0.0.dist-info/METADATA
lyrics_hunter-11.0.0.dist-info/WHEEL
lyrics_hunter-11.0.0.dist-info/top_level.txt
lyrics_hunter-11.0.0.dist-info/RECORD
