Metadata-Version: 2.1
Name: lyrics-hunter
Version: 11.0.0
Summary: Python Lyrics Scrapper
Home-page: UNKNOWN
Author: Ayush Lakra
Author-email: ayushlakra846@gmail.com
License: MIT
Platform: UNKNOWN
Requires-Dist: beautifulsoup4
Requires-Dist: requests
